grenml/__init__.py
grenml/exceptions.py
grenml/managers.py
grenml/parse.py
grenml/write.py
grenml/excel_converter/__init__.py
grenml/excel_converter/convert_excel_to_xml.py
grenml/models/__init__.py
grenml/models/institutions.py
grenml/models/links.py
grenml/models/meta.py
grenml/models/nodes.py
grenml/models/topologies.py
grenml/parsing/__init__.py
grenml/parsing/exceptions.py
grenml/parsing/grenml.py
grenml/parsing/handlers.py
grenml/schemas/__init__.py
grenml/schemas/grenml.xsd
grenml/schemas/nmlbase.xsd
grenml/validation/__init__.py
grenml/validation/validator.py
grenml/writing/__init__.py
grenml/writing/grenml.py
grenml-1.0.2.dist-info/LICENSE
grenml-1.0.2.dist-info/METADATA
grenml-1.0.2.dist-info/WHEEL
grenml-1.0.2.dist-info/top_level.txt
grenml-1.0.2.dist-info/RECORD
