Metadata-Version: 2.1
Name: grenml
Version: 1.0.2
Summary: Library for creating, parsing, and storing GRENML
Home-page: https://github.com/grenmap/grenml
Author: GREN Map Working Group
License: Apache Software License
Keywords: global,network,markup,language,gren,national,research,education,regional,institution,nren
Classifier: Development Status :: 5 - Production/Stable
Classifier: License :: OSI Approved :: Apache Software License
Classifier: Framework :: Flake8
Classifier: Natural Language :: English
Classifier: Operating System :: OS Independent
Classifier: Programming Language :: Python :: 3
Classifier: Programming Language :: Python :: 3.9
Classifier: Topic :: Software Development :: Libraries :: Python Modules
Classifier: Topic :: System :: Networking
Classifier: Topic :: Text Processing :: Markup :: XML
Classifier: Environment :: Console
Classifier: Intended Audience :: Developers
Classifier: Intended Audience :: Telecommunications Industry
Requires-Python: ~=3.9
License-File: LICENSE
Requires-Dist: backports-datetime-fromisoformat ~=1.0
Requires-Dist: python-dateutil ~=2.8
Requires-Dist: lxml ~=4.9.0
Requires-Dist: openpyxl ~=3.0
